pymba/__init__.py
pymba/camera.py
pymba/feature.py
pymba/frame.py
pymba/interface.py
pymba/system.py
pymba/vimba.py
pymba/vimba_c.py
pymba/vimba_exception.py
pymba/vimba_object.py
pymba/vimba_pixelformat.py
pymba-0.3.7.dist-info/LICENSE
pymba-0.3.7.dist-info/METADATA
pymba-0.3.7.dist-info/WHEEL
pymba-0.3.7.dist-info/top_level.txt
pymba-0.3.7.dist-info/RECORD
